{
  "medications": [
    {
      "id": "M001",
      "title": "Frontline Plus",
      "url": "https://www.vetsupply.com.au/",
      "categoryID": "C001",
      "image": "vetsupply",
      "forBreed": ["Toy Poodle", "Pomeranian", "Labrador"],
      "forGender": ["Female", "Male"],
      "forDesexed": [false, true],
      "forAge": [1, 2, 3, 4, 5, 6, 7, 8, 9, 10, 11, 12]
    },
    {
      "id": "M002",
      "title": "Advantage II",
      "url": "https://theanimalpharmacy.com.au/",
      "categoryID": "C001",
      "image": "theanimalpharmacy",
      "forBreed": ["Toy Poodle", "Pomeranian", "Labrador"],
      "forGender": ["Female", "Male"],
      "forDesexed": [false, true],
      "forAge": [1, 2, 3, 4, 5, 6, 7, 8, 9, 10, 11, 12]
    },
    {
      "id": "M003",
      "title": "K9 Advantix II",
      "url": "https://petchemist.com.au/",
      "categoryID": "C001",
      "image": "petchemist",
      "forBreed": ["Toy Poodle", "Pomeranian", "Labrador"],
      "forGender": ["Female", "Male"],
      "forDesexed": [false, true],
      "forAge": [1, 2, 3, 4, 5, 6, 7, 8, 9, 10, 11, 12]
    },
    {
      "id": "M004",
      "title": "Seresto",
      "url": "https://petchemist.com.au/",
      "categoryID": "C002",
      "image": "petchemist",
      "forBreed": ["Toy Poodle", "Pomeranian", "Labrador"],
      "forGender": ["Female", "Male"],
      "forDesexed": [false, true],
      "forAge": [1, 2, 3, 4, 5, 6, 7, 8, 9, 10, 11, 12]
    },
    {
      "id": "M005",
      "title": "Adams Flea & Tick Collar",
      "url": "https://www.vetsupply.com.au/",
      "categoryID": "C002",
      "image": "vetsupply",
      "forBreed": ["Toy Poodle", "Pomeranian", "Labrador"],
      "forGender": ["Female", "Male"],
      "forDesexed": [false, true],
      "forAge": [1, 2, 3, 4, 5, 6, 7, 8, 9, 10, 11, 12]
    },
    {
      "id": "M006",
      "title": "Hartz UltraGuard Pro",
      "url": "https://theanimalpharmacy.com.au/",
      "categoryID": "C002",
      "image": "theanimalpharmacy",
      "forBreed": ["Toy Poodle", "Pomeranian", "Labrador"],
      "forGender": ["Female", "Male"],
      "forDesexed": [false, true],
      "forAge": [1, 2, 3, 4, 5, 6, 7, 8, 9, 10, 11, 12]
    },
    {
      "id": "M007",
      "title": "Frontline Plus",
      "url": "https://www.vetsupply.com.au/",
      "categoryID": "C003",
      "image": "vetsupply",
      "forBreed": ["Toy Poodle", "Pomeranian", "Labrador"],
      "forGender": ["Female", "Male"],
      "forDesexed": [false, true],
      "forAge": [1, 2, 3, 4, 5, 6, 7, 8, 9, 10, 11, 12]
    },
    {
      "id": "M008",
      "title": "Bravecto Topical Solution",
      "url": "https://petchemist.com.au/",
      "categoryID": "C003",
      "image": "petchemist",
      "forBreed": ["Toy Poodle", "Pomeranian", "Labrador"],
      "forGender": ["Female", "Male"],
      "forDesexed": [false, true],
      "forAge": [1, 2, 3, 4, 5, 6, 7, 8, 9, 10, 11, 12]
    },
    {
      "id": "M009",
      "title": "Revolution Plus",
      "url": "https://theanimalpharmacy.com.au/",
      "categoryID": "C003",
      "image": "theanimalpharmacy",
      "forBreed": ["Toy Poodle", "Pomeranian", "Labrador"],
      "forGender": ["Female", "Male"],
      "forDesexed": [false, true],
      "forAge": [1, 2, 3, 4, 5, 6, 7, 8, 9, 10, 11, 12]
    },
    {
      "id": "M010",
      "title": "Seresto",
      "url": "https://www.vetsupply.com.au/",
      "categoryID": "C004",
      "image": "vetsupply",
      "forBreed": ["Toy Poodle", "Pomeranian", "Labrador"],
      "forGender": ["Female", "Male"],
      "forDesexed": [false, true],
      "forAge": [1, 2, 3, 4, 5, 6, 7, 8, 9, 10, 11, 12]
    },
    {
      "id": "M011",
      "title": "Scalibor Protector Band",
      "url": "https://theanimalpharmacy.com.au/",
      "categoryID": "C004",
      "image": "theanimalpharmacy",
      "forBreed": ["Toy Poodle", "Pomeranian", "Labrador"],
      "forGender": ["Female", "Male"],
      "forDesexed": [false, true],
      "forAge": [1, 2, 3, 4, 5, 6, 7, 8, 9, 10, 11, 12]
    },
    {
      "id": "M012",
      "title": "Preventic Tick Collar",
      "url": "https://petchemist.com.au/",
      "categoryID": "C004",
      "image": "petchemist",
      "forBreed": ["Toy Poodle", "Pomeranian", "Labrador"],
      "forGender": ["Female", "Male"],
      "forDesexed": [false, true],
      "forAge": [1, 2, 3, 4, 5, 6, 7, 8, 9, 10, 11, 12]
    },
    {
      "id": "M013",
      "title": "Revolution",
      "url": "https://www.vetsupply.com.au/",
      "categoryID": "C005",
      "image": "vetsupply",
      "forBreed": ["Toy Poodle", "Pomeranian", "Labrador"],
      "forGender": ["Female", "Male"],
      "forDesexed": [false, true],
      "forAge": [1, 2, 3, 4, 5, 6, 7, 8, 9, 10, 11, 12]
    },
    {
      "id": "M014",
      "title": "Advocate (Advantage Multi)",
      "url": "https://petchemist.com.au/",
      "categoryID": "C005",
      "image": "petchemist",
      "forBreed": ["Toy Poodle", "Pomeranian", "Labrador"],
      "forGender": ["Female", "Male"],
      "forDesexed": [false, true],
      "forAge": [1, 2, 3, 4, 5, 6, 7, 8, 9, 10, 11, 12]
    },
    {
      "id": "M015",
      "title": "Bravecto Spot-On",
      "url": "https://theanimalpharmacy.com.au/",
      "categoryID": "C005",
      "image": "theanimalpharmacy",
      "forBreed": ["Toy Poodle", "Pomeranian", "Labrador"],
      "forGender": ["Female", "Male"],
      "forDesexed": [false, true],
      "forAge": [1, 2, 3, 4, 5, 6, 7, 8, 9, 10, 11, 12]
    },
    {
      "id": "M016",
      "title": "Frontline Spray",
      "url": "https://www.vetsupply.com.au/",
      "categoryID": "C006",
      "image": "vetsupply",
      "forBreed": ["Toy Poodle", "Pomeranian", "Labrador"],
      "forGender": ["Female", "Male"],
      "forDesexed": [false, true],
      "forAge": [1, 2, 3, 4, 5, 6, 7, 8, 9, 10, 11, 12]
    },
    {
      "id": "M017",
      "title": "Adams Flea & Tick Spray",
      "url": "https://petchemist.com.au/",
      "categoryID": "C006",
      "image": "petchemist",
      "forBreed": ["Toy Poodle", "Pomeranian", "Labrador"],
      "forGender": ["Female", "Male"],
      "forDesexed": [false, true],
      "forAge": [1, 2, 3, 4, 5, 6, 7, 8, 9, 10, 11, 12]
    },
    {
      "id": "M018",
      "title": "Zodiac Flea & Tick Spray",
      "url": "https://theanimalpharmacy.com.au/",
      "categoryID": "C006",
      "image": "theanimalpharmacy",
      "forBreed": ["Toy Poodle", "Pomeranian", "Labrador"],
      "forGender": ["Female", "Male"],
      "forDesexed": [false, true],
      "forAge": [1, 2, 3, 4, 5, 6, 7, 8, 9, 10, 11, 12]
    },
    {
      "id": "M019",
      "title": "Zymox Otic",
      "url": "https://www.vetsupply.com.au/",
      "categoryID": "C007",
      "image": "vetsupply",
      "forBreed": ["Toy Poodle", "Pomeranian", "Labrador"],
      "forGender": ["Female", "Male"],
      "forDesexed": [false, true],
      "forAge": [1, 2, 3, 4, 5, 6, 7, 8, 9, 10, 11, 12]
    },
    {
      "id": "M020",
      "title": "Tresaderm",
      "url": "https://theanimalpharmacy.com.au/",
      "categoryID": "C007",
      "image": "theanimalpharmacy",
      "forBreed": ["Toy Poodle", "Pomeranian", "Labrador"],
      "forGender": ["Female", "Male"],
      "forDesexed": [false, true],
      "forAge": [1, 2, 3, 4, 5, 6, 7, 8, 9, 10, 11, 12]
    },
    {
      "id": "M021",
      "title": "Mita-Clear",
      "url": "https://petchemist.com.au/",
      "categoryID": "C007",
      "image": "petchemist",
      "forBreed": ["Toy Poodle", "Pomeranian", "Labrador"],
      "forGender": ["Female", "Male"],
      "forDesexed": [false, true],
      "forAge": [1, 2, 3, 4, 5, 6, 7, 8, 9, 10, 11, 12]
    },
    {
      "id": "M022",
      "title": "Revolution",
      "url": "https://www.vetsupply.com.au/",
      "categoryID": "C008",
      "image": "vetsupply",
      "forBreed": ["Toy Poodle", "Pomeranian", "Labrador"],
      "forGender": ["Female", "Male"],
      "forDesexed": [false, true],
      "forAge": [1, 2, 3, 4, 5, 6, 7, 8, 9, 10, 11, 12]
    },
    {
      "id": "M023",
      "title": "Mitaban Dip",
      "url": "https://petchemist.com.au/",
      "categoryID": "C008",
      "image": "petchemist",
      "forBreed": ["Toy Poodle", "Pomeranian", "Labrador"],
      "forGender": ["Female", "Male"],
      "forDesexed": [false, true],
      "forAge": [1, 2, 3, 4, 5, 6, 7, 8, 9, 10, 11, 12]
    },
    {
      "id": "M024",
      "title": "Promeris",
      "url": "https://theanimalpharmacy.com.au/",
      "categoryID": "C008",
      "image": "theanimalpharmacy",
      "forBreed": ["Toy Poodle", "Pomeranian", "Labrador"],
      "forGender": ["Female", "Male"],
      "forDesexed": [false, true],
      "forAge": [1, 2, 3, 4, 5, 6, 7, 8, 9, 10, 11, 12]
    },
    {
      "id": "M025",
      "title": "Heartgard Plus",
      "url": "https://www.vetsupply.com.au/",
      "categoryID": "C009",
      "image": "vetsupply",
      "forBreed": ["Toy Poodle", "Pomeranian", "Labrador"],
      "forGender": ["Female", "Male"],
      "forDesexed": [false, true],
      "forAge": [1, 2, 3, 4, 5, 6, 7, 8, 9, 10, 11, 12]
    },
    {
      "id": "M026",
      "title": "Interceptor Plus",
      "url": "https://theanimalpharmacy.com.au/",
      "categoryID": "C009",
      "image": "theanimalpharmacy",
      "forBreed": ["Toy Poodle", "Pomeranian", "Labrador"],
      "forGender": ["Female", "Male"],
      "forDesexed": [false, true],
      "forAge": [1, 2, 3, 4, 5, 6, 7, 8, 9, 10, 11, 12]
    },
    {
      "id": "M027",
      "title": "Trifexis",
      "url": "https://petchemist.com.au/",
      "categoryID": "C009",
      "image": "petchemist",
      "forBreed": ["Toy Poodle", "Pomeranian", "Labrador"],
      "forGender": ["Female", "Male"],
      "forDesexed": [false, true],
      "forAge": [1, 2, 3, 4, 5, 6, 7, 8, 9, 10, 11, 12]
    },
    {
      "id": "M028",
      "title": "Revolution",
      "url": "https://www.vetsupply.com.au/",
      "categoryID": "C010",
      "image": "vetsupply",
      "forBreed": ["Toy Poodle", "Pomeranian", "Labrador"],
      "forGender": ["Female", "Male"],
      "forDesexed": [false, true],
      "forAge": [1, 2, 3, 4, 5, 6, 7, 8, 9, 10, 11, 12]
    },
    {
      "id": "M029",
      "title": "Advantage Multi",
      "url": "https://petchemist.com.au/",
      "categoryID": "C010",
      "image": "petchemist",
      "forBreed": ["Toy Poodle", "Pomeranian", "Labrador"],
      "forGender": ["Female", "Male"],
      "forDesexed": [false, true],
      "forAge": [1, 2, 3, 4, 5, 6, 7, 8, 9, 10, 11, 12]
    },
    {
      "id": "M030",
      "title": "Selarid",
      "url": "https://theanimalpharmacy.com.au/",
      "categoryID": "C010",
      "image": "theanimalpharmacy",
      "forBreed": ["Toy Poodle", "Pomeranian", "Labrador"],
      "forGender": ["Female", "Male"],
      "forDesexed": [false, true],
      "forAge": [1, 2, 3, 4, 5, 6, 7, 8, 9, 10, 11, 12]
    },
    {
      "id": "M031",
      "title": "Drontal Plus",
      "url": "https://www.vetsupply.com.au/",
      "categoryID": "C011",
      "image": "vetsupply",
      "forBreed": ["Toy Poodle", "Pomeranian", "Labrador"],
      "forGender": ["Female", "Male"],
      "forDesexed": [false, true],
      "forAge": [1, 2, 3, 4, 5, 6, 7, 8, 9, 10, 11, 12]
    },
    {
      "id": "M032",
      "title": "Panacur C",
      "url": "https://petchemist.com.au/",
      "categoryID": "C011",
      "image": "petchemist",
      "forBreed": ["Toy Poodle", "Pomeranian", "Labrador"],
      "forGender": ["Female", "Male"],
      "forDesexed": [false, true],
      "forAge": [1, 2, 3, 4, 5, 6, 7, 8, 9, 10, 11, 12]
    },
    {
      "id": "M033",
      "title": "Nemex 2",
      "url": "https://theanimalpharmacy.com.au/",
      "categoryID": "C011",
      "image": "theanimalpharmacy",
      "forBreed": ["Toy Poodle", "Pomeranian", "Labrador"],
      "forGender": ["Female", "Male"],
      "forDesexed": [false, true],
      "forAge": [1, 2, 3, 4, 5, 6, 7, 8, 9, 10, 11, 12]
    },
    {
      "id": "M034",
      "title": "Metronidazole",
      "url": "https://www.vetsupply.com.au/",
      "categoryID": "C012",
      "image": "vetsupply",
      "forBreed": ["Toy Poodle", "Pomeranian", "Labrador"],
      "forGender": ["Female", "Male"],
      "forDesexed": [false, true],
      "forAge": [1, 2, 3, 4, 5, 6, 7, 8, 9, 10, 11, 12]
    },
    {
      "id": "M035",
      "title": "Panacur (Fenbendazole)",
      "url": "https://theanimalpharmacy.com.au/",
      "categoryID": "C012",
      "image": "theanimalpharmacy",
      "forBreed": ["Toy Poodle", "Pomeranian", "Labrador"],
      "forGender": ["Female", "Male"],
      "forDesexed": [false, true],
      "forAge": [1, 2, 3, 4, 5, 6, 7, 8, 9, 10, 11, 12]
    },
    {
      "id": "M036",
      "title": "Drontal Plus",
      "url": "https://petchemist.com.au/",
      "categoryID": "C012",
      "image": "petchemist",
      "forBreed": ["Toy Poodle", "Pomeranian", "Labrador"],
      "forGender": ["Female", "Male"],
      "forDesexed": [false, true],
      "forAge": [1, 2, 3, 4, 5, 6, 7, 8, 9, 10, 11, 12]
    },
    {
      "id": "M037",
      "title": "Albon (Sulfadimethoxine)",
      "url": "https://www.vetsupply.com.au/",
      "categoryID": "C013",
      "image": "vetsupply",
      "forBreed": ["Toy Poodle", "Pomeranian", "Labrador"],
      "forGender": ["Female", "Male"],
      "forDesexed": [false, true],
      "forAge": [1, 2, 3, 4, 5, 6, 7, 8, 9, 10, 11, 12]
    },
    {
      "id": "M038",
      "title": "Marquis (Ponazuril)",
      "url": "https://petchemist.com.au/",
      "categoryID": "C013",
      "image": "petchemist",
      "forBreed": ["Toy Poodle", "Pomeranian", "Labrador"],
      "forGender": ["Female", "Male"],
      "forDesexed": [false, true],
      "forAge": [1, 2, 3, 4, 5, 6, 7, 8, 9, 10, 11, 12]
    },
    {
      "id": "M039",
      "title": "Tribrissen (Trimethoprim-Sulfa)",
      "url": "https://theanimalpharmacy.com.au/",
      "categoryID": "C013",
      "image": "theanimalpharmacy",
      "forBreed": ["Toy Poodle", "Pomeranian", "Labrador"],
      "forGender": ["Female", "Male"],
      "forDesexed": [false, true],
      "forAge": [1, 2, 3, 4, 5, 6, 7, 8, 9, 10, 11, 12]
    }
  ]
}
